pycameleon/__init__.py
pycameleon/__init__.pyi
pycameleon/py.typed
pycameleon/pycameleon.abi3.so
pycameleon-0.2.7.dist-info/METADATA
pycameleon-0.2.7.dist-info/WHEEL
pycameleon-0.2.7.dist-info/RECORD
