Metadata-Version: 2.4
Name: pycameleon
Version: 0.2.7
License: MIT
